nbne/__init__.py
nbne/get_embeddings.py
nbne/nbne.py
nbne-0.81.dist-info/METADATA
nbne-0.81.dist-info/RECORD
nbne-0.81.dist-info/WHEEL
nbne-0.81.dist-info/entry_points.txt
nbne-0.81.dist-info/top_level.txt
