Metadata-Version: 2.1
Name: nbne
Version: 0.81
Summary: Method to create representations for nodes in a graph, using Neighbor Based Node Embeddings (NBNE) method.
Home-page: https://github.com/tiagopms/nbne
Author: Tiago Pimentel
Author-email: tpimentelms@gmail.com
License: MIT
Keywords: graphs node embeddings machine learning link prediction
Platform: UNKNOWN
Requires-Dist: networkx
Requires-Dist: gensim
